esutils/__init__.py
esutils/code.py
esutils-1.0.0.dist-info/METADATA
esutils-1.0.0.dist-info/WHEEL
esutils-1.0.0.dist-info/licenses/LICENSE
esutils-1.0.0.dist-info/RECORD
